{
    "description": "",
    "tags": [],
    "size": {
        "height": 44,
        "width": 72
    },
    "objects": [
        {
            "id": 908534332,
            "classId": 9997429,
            "description": "",
            "geometryType": "point",
            "labelerLogin": "riadahmed",
            "createdAt": "2022-04-07T09:21:19.600Z",
            "updatedAt": "2022-04-07T09:23:55.048Z",
            "tags": [],
            "classTitle": "a-0",
            "points": {
                "exterior": [
                    [
                        23,
                        9
                    ]
                ],
                "interior": []
            }
        },
        {
            "id": 908534349,
            "classId": 9997482,
            "description": "",
            "geometryType": "point",
            "labelerLogin": "riadahmed",
            "createdAt": "2022-04-07T09:21:26.928Z",
            "updatedAt": "2022-04-07T09:23:55.048Z",
            "tags": [],
            "classTitle": "a-2",
            "points": {
                "exterior": [
                    [
                        53,
                        11
                    ]
                ],
                "interior": []
            }
        },
        {
            "id": 908534366,
            "classId": 9997483,
            "description": "",
            "geometryType": "point",
            "labelerLogin": "riadahmed",
            "createdAt": "2022-04-07T09:21:33.673Z",
            "updatedAt": "2022-04-07T09:23:55.048Z",
            "tags": [],
            "classTitle": "a-3",
            "points": {
                "exterior": [
                    [
                        59,
                        11
                    ]
                ],
                "interior": []
            }
        },
        {
            "id": 908534378,
            "classId": 9997484,
            "description": "",
            "geometryType": "point",
            "labelerLogin": "riadahmed",
            "createdAt": "2022-04-07T09:21:39.184Z",
            "updatedAt": "2022-04-07T09:23:55.048Z",
            "tags": [],
            "classTitle": "a-4",
            "points": {
                "exterior": [
                    [
                        40,
                        24
                    ]
                ],
                "interior": []
            }
        },
        {
            "id": 908534384,
            "classId": 9997485,
            "description": "",
            "geometryType": "point",
            "labelerLogin": "riadahmed",
            "createdAt": "2022-04-07T09:21:44.035Z",
            "updatedAt": "2022-04-07T09:23:55.048Z",
            "tags": [],
            "classTitle": "a-5",
            "points": {
                "exterior": [
                    [
                        48,
                        26
                    ]
                ],
                "interior": []
            }
        },
        {
            "id": 908534392,
            "classId": 9997486,
            "description": "",
            "geometryType": "point",
            "labelerLogin": "riadahmed",
            "createdAt": "2022-04-07T09:21:49.086Z",
            "updatedAt": "2022-04-07T09:23:55.048Z",
            "tags": [],
            "classTitle": "a-6",
            "points": {
                "exterior": [
                    [
                        47,
                        32
                    ]
                ],
                "interior": []
            }
        },
        {
            "id": 908534402,
            "classId": 9997487,
            "description": "",
            "geometryType": "point",
            "labelerLogin": "riadahmed",
            "createdAt": "2022-04-07T09:21:53.673Z",
            "updatedAt": "2022-04-07T09:23:55.048Z",
            "tags": [],
            "classTitle": "a-7",
            "points": {
                "exterior": [
                    [
                        37,
                        42
                    ]
                ],
                "interior": []
            }
        },
        {
            "id": 908534421,
            "classId": 9997488,
            "description": "",
            "geometryType": "point",
            "labelerLogin": "riadahmed",
            "createdAt": "2022-04-07T09:21:57.642Z",
            "updatedAt": "2022-04-07T09:23:55.048Z",
            "tags": [],
            "classTitle": "a-8",
            "points": {
                "exterior": [
                    [
                        24,
                        19
                    ]
                ],
                "interior": []
            }
        },
        {
            "id": 908534648,
            "classId": 9997489,
            "description": "",
            "geometryType": "point",
            "labelerLogin": "riadahmed",
            "createdAt": "2022-04-07T09:23:44.323Z",
            "updatedAt": "2022-04-07T09:23:55.048Z",
            "tags": [],
            "classTitle": "a-9",
            "points": {
                "exterior": [
                    [
                        51,
                        34
                    ]
                ],
                "interior": []
            }
        },
        {
            "id": 908534663,
            "classId": 9997490,
            "description": "",
            "geometryType": "point",
            "labelerLogin": "riadahmed",
            "createdAt": "2022-04-07T09:23:49.635Z",
            "updatedAt": "2022-04-07T09:23:52.668Z",
            "tags": [],
            "classTitle": "a-10",
            "points": {
                "exterior": [
                    [
                        54,
                        40
                    ]
                ],
                "interior": []
            }
        },
        {
            "id": 908534679,
            "classId": 9997491,
            "description": "",
            "geometryType": "point",
            "labelerLogin": "riadahmed",
            "createdAt": "2022-04-07T09:23:54.848Z",
            "updatedAt": "2022-04-07T09:23:54.848Z",
            "tags": [],
            "classTitle": "a-11",
            "points": {
                "exterior": [
                    [
                        56,
                        24
                    ]
                ],
                "interior": []
            }
        }
    ]
}