{
    "description": "",
    "tags": [],
    "size": {
        "height": 46,
        "width": 57
    },
    "objects": [
        {
            "id": 974229008,
            "classId": 10272305,
            "description": "",
            "geometryType": "point",
            "labelerLogin": "Akash2",
            "createdAt": "2022-07-22T04:56:36.893Z",
            "updatedAt": "2022-07-22T04:56:46.615Z",
            "tags": [],
            "classTitle": "0",
            "points": {
                "exterior": [
                    [
                        27,
                        20
                    ]
                ],
                "interior": []
            }
        },
        {
            "id": 974229009,
            "classId": 10272306,
            "description": "",
            "geometryType": "point",
            "labelerLogin": "Akash2",
            "createdAt": "2022-07-22T04:56:38.483Z",
            "updatedAt": "2022-07-22T04:56:45.425Z",
            "tags": [],
            "classTitle": "1",
            "points": {
                "exterior": [
                    [
                        25,
                        17
                    ]
                ],
                "interior": []
            }
        },
        {
            "id": 974229012,
            "classId": 10272307,
            "description": "",
            "geometryType": "point",
            "labelerLogin": "Akash2",
            "createdAt": "2022-07-22T04:56:39.637Z",
            "updatedAt": "2022-07-22T04:56:46.615Z",
            "tags": [],
            "classTitle": "2",
            "points": {
                "exterior": [
                    [
                        39,
                        14
                    ]
                ],
                "interior": []
            }
        },
        {
            "id": 974229015,
            "classId": 10272308,
            "description": "",
            "geometryType": "point",
            "labelerLogin": "Akash2",
            "createdAt": "2022-07-22T04:56:40.660Z",
            "updatedAt": "2022-07-22T04:56:44.315Z",
            "tags": [],
            "classTitle": "3",
            "points": {
                "exterior": [
                    [
                        40,
                        24
                    ]
                ],
                "interior": []
            }
        },
        {
            "id": 974229016,
            "classId": 10272309,
            "description": "",
            "geometryType": "point",
            "labelerLogin": "Akash2",
            "createdAt": "2022-07-22T04:56:41.562Z",
            "updatedAt": "2022-07-22T04:56:45.425Z",
            "tags": [],
            "classTitle": "4",
            "points": {
                "exterior": [
                    [
                        37,
                        26
                    ]
                ],
                "interior": []
            }
        },
        {
            "id": 974229019,
            "classId": 10272310,
            "description": "",
            "geometryType": "point",
            "labelerLogin": "Akash2",
            "createdAt": "2022-07-22T04:56:42.938Z",
            "updatedAt": "2022-07-22T04:56:46.615Z",
            "tags": [],
            "classTitle": "5",
            "points": {
                "exterior": [
                    [
                        41,
                        34
                    ]
                ],
                "interior": []
            }
        },
        {
            "id": 974229021,
            "classId": 10272311,
            "description": "",
            "geometryType": "point",
            "labelerLogin": "Akash2",
            "createdAt": "2022-07-22T04:56:44.067Z",
            "updatedAt": "2022-07-22T04:56:44.067Z",
            "tags": [],
            "classTitle": "6",
            "points": {
                "exterior": [
                    [
                        34,
                        40
                    ]
                ],
                "interior": []
            }
        },
        {
            "id": 974229023,
            "classId": 10272312,
            "description": "",
            "geometryType": "point",
            "labelerLogin": "Akash2",
            "createdAt": "2022-07-22T04:56:45.167Z",
            "updatedAt": "2022-07-22T04:56:45.167Z",
            "tags": [],
            "classTitle": "7",
            "points": {
                "exterior": [
                    [
                        25,
                        32
                    ]
                ],
                "interior": []
            }
        },
        {
            "id": 974229025,
            "classId": 10272313,
            "description": "",
            "geometryType": "point",
            "labelerLogin": "Akash2",
            "createdAt": "2022-07-22T04:56:46.360Z",
            "updatedAt": "2022-07-22T04:56:46.360Z",
            "tags": [],
            "classTitle": "8",
            "points": {
                "exterior": [
                    [
                        17,
                        23
                    ]
                ],
                "interior": []
            }
        }
    ]
}