{
    "description": "",
    "tags": [],
    "size": {
        "height": 97,
        "width": 137
    },
    "objects": [
        {
            "id": 971673693,
            "classId": 10255513,
            "description": "",
            "geometryType": "point",
            "labelerLogin": "Akash2",
            "createdAt": "2022-07-17T12:13:29.413Z",
            "updatedAt": "2022-07-17T12:13:50.221Z",
            "tags": [],
            "classTitle": "0",
            "points": {
                "exterior": [
                    [
                        36,
                        25
                    ]
                ],
                "interior": []
            }
        },
        {
            "id": 971673695,
            "classId": 10255514,
            "description": "",
            "geometryType": "point",
            "labelerLogin": "Akash2",
            "createdAt": "2022-07-17T12:13:31.049Z",
            "updatedAt": "2022-07-17T12:13:50.221Z",
            "tags": [],
            "classTitle": "1",
            "points": {
                "exterior": [
                    [
                        47,
                        33
                    ]
                ],
                "interior": []
            }
        },
        {
            "id": 971673697,
            "classId": 10255515,
            "description": "",
            "geometryType": "point",
            "labelerLogin": "Akash2",
            "createdAt": "2022-07-17T12:13:32.195Z",
            "updatedAt": "2022-07-17T12:13:50.221Z",
            "tags": [],
            "classTitle": "2",
            "points": {
                "exterior": [
                    [
                        61,
                        25
                    ]
                ],
                "interior": []
            }
        },
        {
            "id": 971673699,
            "classId": 10255516,
            "description": "",
            "geometryType": "point",
            "labelerLogin": "Akash2",
            "createdAt": "2022-07-17T12:13:33.393Z",
            "updatedAt": "2022-07-17T12:13:50.221Z",
            "tags": [],
            "classTitle": "3",
            "points": {
                "exterior": [
                    [
                        65,
                        35
                    ]
                ],
                "interior": []
            }
        },
        {
            "id": 971673702,
            "classId": 10255517,
            "description": "",
            "geometryType": "point",
            "labelerLogin": "Akash2",
            "createdAt": "2022-07-17T12:13:36.254Z",
            "updatedAt": "2022-07-17T12:13:50.221Z",
            "tags": [],
            "classTitle": "4",
            "points": {
                "exterior": [
                    [
                        83,
                        15
                    ]
                ],
                "interior": []
            }
        },
        {
            "id": 971673704,
            "classId": 10255518,
            "description": "",
            "geometryType": "point",
            "labelerLogin": "Akash2",
            "createdAt": "2022-07-17T12:13:37.951Z",
            "updatedAt": "2022-07-17T12:13:48.624Z",
            "tags": [],
            "classTitle": "5",
            "points": {
                "exterior": [
                    [
                        80,
                        27
                    ]
                ],
                "interior": []
            }
        },
        {
            "id": 971673705,
            "classId": 10255519,
            "description": "",
            "geometryType": "point",
            "labelerLogin": "Akash2",
            "createdAt": "2022-07-17T12:13:39.339Z",
            "updatedAt": "2022-07-17T12:13:50.221Z",
            "tags": [],
            "classTitle": "6",
            "points": {
                "exterior": [
                    [
                        45,
                        48
                    ]
                ],
                "interior": []
            }
        },
        {
            "id": 971673707,
            "classId": 10255520,
            "description": "",
            "geometryType": "point",
            "labelerLogin": "Akash2",
            "createdAt": "2022-07-17T12:13:41.081Z",
            "updatedAt": "2022-07-17T12:13:48.624Z",
            "tags": [],
            "classTitle": "7",
            "points": {
                "exterior": [
                    [
                        75,
                        81
                    ]
                ],
                "interior": []
            }
        },
        {
            "id": 971673709,
            "classId": 10255521,
            "description": "",
            "geometryType": "point",
            "labelerLogin": "Akash2",
            "createdAt": "2022-07-17T12:13:43.258Z",
            "updatedAt": "2022-07-17T12:13:50.221Z",
            "tags": [],
            "classTitle": "8",
            "points": {
                "exterior": [
                    [
                        78,
                        52
                    ]
                ],
                "interior": []
            }
        },
        {
            "id": 971673712,
            "classId": 10255522,
            "description": "",
            "geometryType": "point",
            "labelerLogin": "Akash2",
            "createdAt": "2022-07-17T12:13:44.894Z",
            "updatedAt": "2022-07-17T12:13:48.624Z",
            "tags": [],
            "classTitle": "9",
            "points": {
                "exterior": [
                    [
                        96,
                        81
                    ]
                ],
                "interior": []
            }
        },
        {
            "id": 971673715,
            "classId": 10255523,
            "description": "",
            "geometryType": "point",
            "labelerLogin": "Akash2",
            "createdAt": "2022-07-17T12:13:46.858Z",
            "updatedAt": "2022-07-17T12:13:50.221Z",
            "tags": [],
            "classTitle": "10",
            "points": {
                "exterior": [
                    [
                        98,
                        8
                    ]
                ],
                "interior": []
            }
        },
        {
            "id": 971673716,
            "classId": 10255524,
            "description": "",
            "geometryType": "point",
            "labelerLogin": "Akash2",
            "createdAt": "2022-07-17T12:13:48.399Z",
            "updatedAt": "2022-07-17T12:13:48.399Z",
            "tags": [],
            "classTitle": "11",
            "points": {
                "exterior": [
                    [
                        100,
                        26
                    ]
                ],
                "interior": []
            }
        },
        {
            "id": 971673717,
            "classId": 10255525,
            "description": "",
            "geometryType": "point",
            "labelerLogin": "Akash2",
            "createdAt": "2022-07-17T12:13:49.964Z",
            "updatedAt": "2022-07-17T12:13:49.964Z",
            "tags": [],
            "classTitle": "12",
            "points": {
                "exterior": [
                    [
                        123,
                        19
                    ]
                ],
                "interior": []
            }
        }
    ]
}