{
    "description": "",
    "tags": [],
    "size": {
        "height": 67,
        "width": 102
    },
    "objects": [
        {
            "id": 965767937,
            "classId": 10242338,
            "description": "",
            "geometryType": "point",
            "labelerLogin": "ShamaetaPaul",
            "createdAt": "2022-07-12T05:00:44.559Z",
            "updatedAt": "2022-07-12T05:01:02.822Z",
            "tags": [],
            "classTitle": "0",
            "points": {
                "exterior": [
                    [
                        14,
                        21
                    ]
                ],
                "interior": []
            }
        },
        {
            "id": 965767940,
            "classId": 10242340,
            "description": "",
            "geometryType": "point",
            "labelerLogin": "ShamaetaPaul",
            "createdAt": "2022-07-12T05:00:47.779Z",
            "updatedAt": "2022-07-12T05:01:02.822Z",
            "tags": [],
            "classTitle": "2",
            "points": {
                "exterior": [
                    [
                        56,
                        22
                    ]
                ],
                "interior": []
            }
        },
        {
            "id": 965767942,
            "classId": 10242341,
            "description": "",
            "geometryType": "point",
            "labelerLogin": "ShamaetaPaul",
            "createdAt": "2022-07-12T05:00:48.859Z",
            "updatedAt": "2022-07-12T05:01:04.277Z",
            "tags": [],
            "classTitle": "3",
            "points": {
                "exterior": [
                    [
                        65,
                        21
                    ]
                ],
                "interior": []
            }
        },
        {
            "id": 965767944,
            "classId": 10242342,
            "description": "",
            "geometryType": "point",
            "labelerLogin": "ShamaetaPaul",
            "createdAt": "2022-07-12T05:00:50.306Z",
            "updatedAt": "2022-07-12T05:01:04.277Z",
            "tags": [],
            "classTitle": "4",
            "points": {
                "exterior": [
                    [
                        80,
                        23
                    ]
                ],
                "interior": []
            }
        },
        {
            "id": 965767948,
            "classId": 10242343,
            "description": "",
            "geometryType": "point",
            "labelerLogin": "ShamaetaPaul",
            "createdAt": "2022-07-12T05:00:51.600Z",
            "updatedAt": "2022-07-12T05:01:02.822Z",
            "tags": [],
            "classTitle": "5",
            "points": {
                "exterior": [
                    [
                        43,
                        32
                    ]
                ],
                "interior": []
            }
        },
        {
            "id": 965767950,
            "classId": 10242344,
            "description": "",
            "geometryType": "point",
            "labelerLogin": "ShamaetaPaul",
            "createdAt": "2022-07-12T05:00:53.815Z",
            "updatedAt": "2022-07-12T05:01:04.277Z",
            "tags": [],
            "classTitle": "6",
            "points": {
                "exterior": [
                    [
                        52,
                        33
                    ]
                ],
                "interior": []
            }
        },
        {
            "id": 965767951,
            "classId": 10242345,
            "description": "",
            "geometryType": "point",
            "labelerLogin": "ShamaetaPaul",
            "createdAt": "2022-07-12T05:00:54.878Z",
            "updatedAt": "2022-07-12T05:01:02.822Z",
            "tags": [],
            "classTitle": "7",
            "points": {
                "exterior": [
                    [
                        52,
                        39
                    ]
                ],
                "interior": []
            }
        },
        {
            "id": 965767954,
            "classId": 10242346,
            "description": "",
            "geometryType": "point",
            "labelerLogin": "ShamaetaPaul",
            "createdAt": "2022-07-12T05:00:55.957Z",
            "updatedAt": "2022-07-12T05:01:02.822Z",
            "tags": [],
            "classTitle": "8",
            "points": {
                "exterior": [
                    [
                        42,
                        50
                    ]
                ],
                "interior": []
            }
        },
        {
            "id": 965767955,
            "classId": 10242347,
            "description": "",
            "geometryType": "point",
            "labelerLogin": "ShamaetaPaul",
            "createdAt": "2022-07-12T05:00:57.193Z",
            "updatedAt": "2022-07-12T05:01:04.277Z",
            "tags": [],
            "classTitle": "9",
            "points": {
                "exterior": [
                    [
                        23,
                        27
                    ]
                ],
                "interior": []
            }
        },
        {
            "id": 965767957,
            "classId": 10242348,
            "description": "",
            "geometryType": "point",
            "labelerLogin": "ShamaetaPaul",
            "createdAt": "2022-07-12T05:00:58.737Z",
            "updatedAt": "2022-07-12T05:01:02.822Z",
            "tags": [],
            "classTitle": "10",
            "points": {
                "exterior": [
                    [
                        59,
                        42
                    ]
                ],
                "interior": []
            }
        },
        {
            "id": 965767959,
            "classId": 10242349,
            "description": "",
            "geometryType": "point",
            "labelerLogin": "ShamaetaPaul",
            "createdAt": "2022-07-12T05:01:00.289Z",
            "updatedAt": "2022-07-12T05:01:04.277Z",
            "tags": [],
            "classTitle": "11",
            "points": {
                "exterior": [
                    [
                        67,
                        51
                    ]
                ],
                "interior": []
            }
        },
        {
            "id": 965767960,
            "classId": 10242350,
            "description": "",
            "geometryType": "point",
            "labelerLogin": "ShamaetaPaul",
            "createdAt": "2022-07-12T05:01:01.407Z",
            "updatedAt": "2022-07-12T05:01:01.407Z",
            "tags": [],
            "classTitle": "12",
            "points": {
                "exterior": [
                    [
                        65,
                        35
                    ]
                ],
                "interior": []
            }
        },
        {
            "id": 965767963,
            "classId": 10242351,
            "description": "",
            "geometryType": "point",
            "labelerLogin": "ShamaetaPaul",
            "createdAt": "2022-07-12T05:01:02.608Z",
            "updatedAt": "2022-07-12T05:01:02.608Z",
            "tags": [],
            "classTitle": "13",
            "points": {
                "exterior": [
                    [
                        79,
                        34
                    ]
                ],
                "interior": []
            }
        },
        {
            "id": 965767964,
            "classId": 10242352,
            "description": "",
            "geometryType": "point",
            "labelerLogin": "ShamaetaPaul",
            "createdAt": "2022-07-12T05:01:04.059Z",
            "updatedAt": "2022-07-12T05:01:04.059Z",
            "tags": [],
            "classTitle": "14",
            "points": {
                "exterior": [
                    [
                        81,
                        50
                    ]
                ],
                "interior": []
            }
        }
    ]
}