{
    "description": "",
    "tags": [],
    "size": {
        "height": 79,
        "width": 106
    },
    "objects": [
        {
            "id": 971677806,
            "classId": 10255513,
            "description": "",
            "geometryType": "point",
            "labelerLogin": "Akash2",
            "createdAt": "2022-07-17T12:48:58.236Z",
            "updatedAt": "2022-07-17T12:49:10.452Z",
            "tags": [],
            "classTitle": "0",
            "points": {
                "exterior": [
                    [
                        32,
                        28
                    ]
                ],
                "interior": []
            }
        },
        {
            "id": 971677808,
            "classId": 10255514,
            "description": "",
            "geometryType": "point",
            "labelerLogin": "Akash2",
            "createdAt": "2022-07-17T12:48:59.833Z",
            "updatedAt": "2022-07-17T12:49:10.452Z",
            "tags": [],
            "classTitle": "1",
            "points": {
                "exterior": [
                    [
                        38,
                        30
                    ]
                ],
                "interior": []
            }
        },
        {
            "id": 971677809,
            "classId": 10255515,
            "description": "",
            "geometryType": "point",
            "labelerLogin": "Akash2",
            "createdAt": "2022-07-17T12:49:00.709Z",
            "updatedAt": "2022-07-17T12:49:12.033Z",
            "tags": [],
            "classTitle": "2",
            "points": {
                "exterior": [
                    [
                        42,
                        24
                    ]
                ],
                "interior": []
            }
        },
        {
            "id": 971677812,
            "classId": 10255516,
            "description": "",
            "geometryType": "point",
            "labelerLogin": "Akash2",
            "createdAt": "2022-07-17T12:49:01.690Z",
            "updatedAt": "2022-07-17T12:49:10.452Z",
            "tags": [],
            "classTitle": "3",
            "points": {
                "exterior": [
                    [
                        48,
                        30
                    ]
                ],
                "interior": []
            }
        },
        {
            "id": 971677813,
            "classId": 10255517,
            "description": "",
            "geometryType": "point",
            "labelerLogin": "Akash2",
            "createdAt": "2022-07-17T12:49:02.680Z",
            "updatedAt": "2022-07-17T12:49:10.452Z",
            "tags": [],
            "classTitle": "4",
            "points": {
                "exterior": [
                    [
                        49,
                        23
                    ]
                ],
                "interior": []
            }
        },
        {
            "id": 971677814,
            "classId": 10255518,
            "description": "",
            "geometryType": "point",
            "labelerLogin": "Akash2",
            "createdAt": "2022-07-17T12:49:03.673Z",
            "updatedAt": "2022-07-17T12:49:12.033Z",
            "tags": [],
            "classTitle": "5",
            "points": {
                "exterior": [
                    [
                        49,
                        30
                    ]
                ],
                "interior": []
            }
        },
        {
            "id": 971677816,
            "classId": 10255519,
            "description": "",
            "geometryType": "point",
            "labelerLogin": "Akash2",
            "createdAt": "2022-07-17T12:49:05.077Z",
            "updatedAt": "2022-07-17T12:49:10.452Z",
            "tags": [],
            "classTitle": "6",
            "points": {
                "exterior": [
                    [
                        23,
                        44
                    ]
                ],
                "interior": []
            }
        },
        {
            "id": 971677819,
            "classId": 10255520,
            "description": "",
            "geometryType": "point",
            "labelerLogin": "Akash2",
            "createdAt": "2022-07-17T12:49:06.423Z",
            "updatedAt": "2022-07-17T12:49:10.452Z",
            "tags": [],
            "classTitle": "7",
            "points": {
                "exterior": [
                    [
                        59,
                        55
                    ]
                ],
                "interior": []
            }
        },
        {
            "id": 971677820,
            "classId": 10255521,
            "description": "",
            "geometryType": "point",
            "labelerLogin": "Akash2",
            "createdAt": "2022-07-17T12:49:07.588Z",
            "updatedAt": "2022-07-17T12:49:12.033Z",
            "tags": [],
            "classTitle": "8",
            "points": {
                "exterior": [
                    [
                        57,
                        45
                    ]
                ],
                "interior": []
            }
        },
        {
            "id": 971677821,
            "classId": 10255522,
            "description": "",
            "geometryType": "point",
            "labelerLogin": "Akash2",
            "createdAt": "2022-07-17T12:49:10.226Z",
            "updatedAt": "2022-07-17T12:49:13.246Z",
            "tags": [],
            "classTitle": "9",
            "points": {
                "exterior": [
                    [
                        70,
                        50
                    ]
                ],
                "interior": []
            }
        },
        {
            "id": 971677823,
            "classId": 10255524,
            "description": "",
            "geometryType": "point",
            "labelerLogin": "Akash2",
            "createdAt": "2022-07-17T12:49:11.811Z",
            "updatedAt": "2022-07-17T12:49:11.811Z",
            "tags": [],
            "classTitle": "11",
            "points": {
                "exterior": [
                    [
                        62,
                        22
                    ]
                ],
                "interior": []
            }
        },
        {
            "id": 971677825,
            "classId": 10255525,
            "description": "",
            "geometryType": "point",
            "labelerLogin": "Akash2",
            "createdAt": "2022-07-17T12:49:13.032Z",
            "updatedAt": "2022-07-17T12:49:13.032Z",
            "tags": [],
            "classTitle": "12",
            "points": {
                "exterior": [
                    [
                        80,
                        21
                    ]
                ],
                "interior": []
            }
        }
    ]
}