{
    "description": "",
    "tags": [],
    "size": {
        "height": 76,
        "width": 91
    },
    "objects": [
        {
            "id": 974155774,
            "classId": 10260847,
            "description": "",
            "geometryType": "point",
            "labelerLogin": "Zibat",
            "createdAt": "2022-07-21T20:30:28.327Z",
            "updatedAt": "2022-07-21T20:30:44.647Z",
            "tags": [],
            "classTitle": "0",
            "points": {
                "exterior": [
                    [
                        46,
                        30
                    ]
                ],
                "interior": []
            }
        },
        {
            "id": 974155777,
            "classId": 10260848,
            "description": "",
            "geometryType": "point",
            "labelerLogin": "Zibat",
            "createdAt": "2022-07-21T20:30:31.108Z",
            "updatedAt": "2022-07-21T20:30:44.647Z",
            "tags": [],
            "classTitle": "1",
            "points": {
                "exterior": [
                    [
                        52,
                        20
                    ]
                ],
                "interior": []
            }
        },
        {
            "id": 974155779,
            "classId": 10260849,
            "description": "",
            "geometryType": "point",
            "labelerLogin": "Zibat",
            "createdAt": "2022-07-21T20:30:34.101Z",
            "updatedAt": "2022-07-21T20:30:44.647Z",
            "tags": [],
            "classTitle": "2",
            "points": {
                "exterior": [
                    [
                        56,
                        37
                    ]
                ],
                "interior": []
            }
        },
        {
            "id": 974155782,
            "classId": 10260850,
            "description": "",
            "geometryType": "point",
            "labelerLogin": "Zibat",
            "createdAt": "2022-07-21T20:30:36.130Z",
            "updatedAt": "2022-07-21T20:30:44.647Z",
            "tags": [],
            "classTitle": "3",
            "points": {
                "exterior": [
                    [
                        57,
                        55
                    ]
                ],
                "interior": []
            }
        },
        {
            "id": 974155785,
            "classId": 10260851,
            "description": "",
            "geometryType": "point",
            "labelerLogin": "Zibat",
            "createdAt": "2022-07-21T20:30:38.148Z",
            "updatedAt": "2022-07-21T20:30:44.647Z",
            "tags": [],
            "classTitle": "4",
            "points": {
                "exterior": [
                    [
                        50,
                        48
                    ]
                ],
                "interior": []
            }
        },
        {
            "id": 974155790,
            "classId": 10260852,
            "description": "",
            "geometryType": "point",
            "labelerLogin": "Zibat",
            "createdAt": "2022-07-21T20:30:44.303Z",
            "updatedAt": "2022-07-21T20:30:44.303Z",
            "tags": [],
            "classTitle": "5",
            "points": {
                "exterior": [
                    [
                        31,
                        57
                    ]
                ],
                "interior": []
            }
        },
        {
            "id": 974155792,
            "classId": 10260853,
            "description": "",
            "geometryType": "point",
            "labelerLogin": "Zibat",
            "createdAt": "2022-07-21T20:30:46.247Z",
            "updatedAt": "2022-07-21T20:30:46.247Z",
            "tags": [],
            "classTitle": "6",
            "points": {
                "exterior": [
                    [
                        21,
                        43
                    ]
                ],
                "interior": []
            }
        }
    ]
}