{
    "description": "",
    "tags": [],
    "size": {
        "height": 49,
        "width": 57
    },
    "objects": [
        {
            "id": 974677908,
            "classId": 10273716,
            "description": "",
            "geometryType": "point",
            "labelerLogin": "Akash2",
            "createdAt": "2022-07-23T18:29:31.218Z",
            "updatedAt": "2022-07-23T18:30:15.751Z",
            "tags": [],
            "classTitle": "0",
            "points": {
                "exterior": [
                    [
                        28,
                        20
                    ]
                ],
                "interior": []
            }
        },
        {
            "id": 974677909,
            "classId": 10273717,
            "description": "",
            "geometryType": "point",
            "labelerLogin": "Akash2",
            "createdAt": "2022-07-23T18:29:32.717Z",
            "updatedAt": "2022-07-23T18:30:15.751Z",
            "tags": [],
            "classTitle": "1",
            "points": {
                "exterior": [
                    [
                        31,
                        17
                    ]
                ],
                "interior": []
            }
        },
        {
            "id": 974677910,
            "classId": 10273719,
            "description": "",
            "geometryType": "point",
            "labelerLogin": "Akash2",
            "createdAt": "2022-07-23T18:29:35.522Z",
            "updatedAt": "2022-07-23T18:30:15.751Z",
            "tags": [],
            "classTitle": "2",
            "points": {
                "exterior": [
                    [
                        34,
                        20
                    ]
                ],
                "interior": []
            }
        },
        {
            "id": 974677912,
            "classId": 10273720,
            "description": "",
            "geometryType": "point",
            "labelerLogin": "Akash2",
            "createdAt": "2022-07-23T18:29:40.506Z",
            "updatedAt": "2022-07-23T18:30:15.751Z",
            "tags": [],
            "classTitle": "3",
            "points": {
                "exterior": [
                    [
                        33,
                        27
                    ]
                ],
                "interior": []
            }
        },
        {
            "id": 974677928,
            "classId": 10273722,
            "description": "",
            "geometryType": "point",
            "labelerLogin": "Akash2",
            "createdAt": "2022-07-23T18:29:55.494Z",
            "updatedAt": "2022-07-23T18:30:15.751Z",
            "tags": [],
            "classTitle": "5",
            "points": {
                "exterior": [
                    [
                        34,
                        32
                    ]
                ],
                "interior": []
            }
        },
        {
            "id": 974677931,
            "classId": 10273723,
            "description": "",
            "geometryType": "point",
            "labelerLogin": "Akash2",
            "createdAt": "2022-07-23T18:29:58.096Z",
            "updatedAt": "2022-07-23T18:30:15.751Z",
            "tags": [],
            "classTitle": "6",
            "points": {
                "exterior": [
                    [
                        26,
                        36
                    ]
                ],
                "interior": []
            }
        },
        {
            "id": 974677933,
            "classId": 10273724,
            "description": "",
            "geometryType": "point",
            "labelerLogin": "Akash2",
            "createdAt": "2022-07-23T18:30:00.226Z",
            "updatedAt": "2022-07-23T18:30:15.751Z",
            "tags": [],
            "classTitle": "7",
            "points": {
                "exterior": [
                    [
                        17,
                        32
                    ]
                ],
                "interior": []
            }
        },
        {
            "id": 974677938,
            "classId": 10273725,
            "description": "",
            "geometryType": "point",
            "labelerLogin": "Akash2",
            "createdAt": "2022-07-23T18:30:02.220Z",
            "updatedAt": "2022-07-23T18:30:15.751Z",
            "tags": [],
            "classTitle": "8",
            "points": {
                "exterior": [
                    [
                        15,
                        23
                    ]
                ],
                "interior": []
            }
        },
        {
            "id": 974677943,
            "classId": 10273726,
            "description": "",
            "geometryType": "point",
            "labelerLogin": "Akash2",
            "createdAt": "2022-07-23T18:30:07.533Z",
            "updatedAt": "2022-07-23T18:30:15.751Z",
            "tags": [],
            "classTitle": "9",
            "points": {
                "exterior": [
                    [
                        45,
                        19
                    ]
                ],
                "interior": []
            }
        },
        {
            "id": 974677950,
            "classId": 10273728,
            "description": "",
            "geometryType": "point",
            "labelerLogin": "Akash2",
            "createdAt": "2022-07-23T18:30:15.442Z",
            "updatedAt": "2022-07-23T18:30:15.442Z",
            "tags": [],
            "classTitle": "10",
            "points": {
                "exterior": [
                    [
                        26,
                        11
                    ]
                ],
                "interior": []
            }
        },
        {
            "id": 974677953,
            "classId": 10273729,
            "description": "",
            "geometryType": "point",
            "labelerLogin": "Akash2",
            "createdAt": "2022-07-23T18:30:17.261Z",
            "updatedAt": "2022-07-23T18:30:17.261Z",
            "tags": [],
            "classTitle": "11",
            "points": {
                "exterior": [
                    [
                        28,
                        3
                    ]
                ],
                "interior": []
            }
        }
    ]
}