{
    "description": "",
    "tags": [],
    "size": {
        "height": 41,
        "width": 70
    },
    "objects": [
        {
            "id": 942276735,
            "classId": 10129806,
            "description": "",
            "geometryType": "point",
            "labelerLogin": "Ipshita",
            "createdAt": "2022-05-29T04:28:04.495Z",
            "updatedAt": "2022-05-29T04:28:48.626Z",
            "tags": [],
            "classTitle": "c-0",
            "points": {
                "exterior": [
                    [
                        16,
                        17
                    ]
                ],
                "interior": []
            }
        },
        {
            "id": 942276738,
            "classId": 10129808,
            "description": "",
            "geometryType": "point",
            "labelerLogin": "Ipshita",
            "createdAt": "2022-05-29T04:28:14.413Z",
            "updatedAt": "2022-05-29T04:28:48.626Z",
            "tags": [],
            "classTitle": "c-2",
            "points": {
                "exterior": [
                    [
                        35,
                        17
                    ]
                ],
                "interior": []
            }
        },
        {
            "id": 942276739,
            "classId": 10129809,
            "description": "",
            "geometryType": "point",
            "labelerLogin": "Ipshita",
            "createdAt": "2022-05-29T04:28:19.905Z",
            "updatedAt": "2022-05-29T04:28:48.626Z",
            "tags": [],
            "classTitle": "c-3",
            "points": {
                "exterior": [
                    [
                        47,
                        17
                    ]
                ],
                "interior": []
            }
        },
        {
            "id": 942276740,
            "classId": 10129810,
            "description": "",
            "geometryType": "point",
            "labelerLogin": "Ipshita",
            "createdAt": "2022-05-29T04:28:23.341Z",
            "updatedAt": "2022-05-29T04:28:48.626Z",
            "tags": [],
            "classTitle": "c-4",
            "points": {
                "exterior": [
                    [
                        32,
                        26
                    ]
                ],
                "interior": []
            }
        },
        {
            "id": 942276741,
            "classId": 10129811,
            "description": "",
            "geometryType": "point",
            "labelerLogin": "Ipshita",
            "createdAt": "2022-05-29T04:28:26.376Z",
            "updatedAt": "2022-05-29T04:28:48.626Z",
            "tags": [],
            "classTitle": "c-5",
            "points": {
                "exterior": [
                    [
                        41,
                        27
                    ]
                ],
                "interior": []
            }
        },
        {
            "id": 942276742,
            "classId": 10129812,
            "description": "",
            "geometryType": "point",
            "labelerLogin": "Ipshita",
            "createdAt": "2022-05-29T04:28:29.246Z",
            "updatedAt": "2022-05-29T04:28:48.626Z",
            "tags": [],
            "classTitle": "c-6",
            "points": {
                "exterior": [
                    [
                        28,
                        36
                    ]
                ],
                "interior": []
            }
        },
        {
            "id": 942276744,
            "classId": 10129813,
            "description": "",
            "geometryType": "point",
            "labelerLogin": "Ipshita",
            "createdAt": "2022-05-29T04:28:32.510Z",
            "updatedAt": "2022-05-29T04:28:48.626Z",
            "tags": [],
            "classTitle": "c-7",
            "points": {
                "exterior": [
                    [
                        38,
                        36
                    ]
                ],
                "interior": []
            }
        },
        {
            "id": 942276745,
            "classId": 10129814,
            "description": "",
            "geometryType": "point",
            "labelerLogin": "Ipshita",
            "createdAt": "2022-05-29T04:28:35.006Z",
            "updatedAt": "2022-05-29T04:28:48.626Z",
            "tags": [],
            "classTitle": "c-8",
            "points": {
                "exterior": [
                    [
                        44,
                        40
                    ]
                ],
                "interior": []
            }
        },
        {
            "id": 942276746,
            "classId": 10129815,
            "description": "",
            "geometryType": "point",
            "labelerLogin": "Ipshita",
            "createdAt": "2022-05-29T04:28:41.623Z",
            "updatedAt": "2022-05-29T04:28:48.626Z",
            "tags": [],
            "classTitle": "c-9",
            "points": {
                "exterior": [
                    [
                        38,
                        10
                    ]
                ],
                "interior": []
            }
        },
        {
            "id": 942276747,
            "classId": 10129816,
            "description": "",
            "geometryType": "point",
            "labelerLogin": "Ipshita",
            "createdAt": "2022-05-29T04:28:44.845Z",
            "updatedAt": "2022-05-29T04:28:48.626Z",
            "tags": [],
            "classTitle": "c-10",
            "points": {
                "exterior": [
                    [
                        30,
                        6
                    ]
                ],
                "interior": []
            }
        },
        {
            "id": 942276748,
            "classId": 10129818,
            "description": "",
            "geometryType": "point",
            "labelerLogin": "Ipshita",
            "createdAt": "2022-05-29T04:28:48.330Z",
            "updatedAt": "2022-05-29T04:28:48.330Z",
            "tags": [],
            "classTitle": "c-11",
            "points": {
                "exterior": [
                    [
                        26,
                        2
                    ]
                ],
                "interior": []
            }
        }
    ]
}